shocker/__init__.py
shocker-0.1.1.dist-info/LICENSE
shocker-0.1.1.dist-info/METADATA
shocker-0.1.1.dist-info/WHEEL
shocker-0.1.1.dist-info/top_level.txt
shocker-0.1.1.dist-info/RECORD
